sunsolve/__init__.py
sunsolve/fitness_function.py
sunsolve/genetic_algorithm.py
sunsolve/plotter.py
sunsolve/solver.py
sunsolve-0.0.4.dist-info/METADATA
sunsolve-0.0.4.dist-info/WHEEL
sunsolve-0.0.4.dist-info/RECORD
