Metadata-Version: 2.1
Name: sunsolve
Version: 0.0.4
Summary: A python package for solving the inverse problem of matching LEDs to the sun’s spectrum
Home-page: https://nkalis.github.io/sunsolve
License: MIT
Author: nkalis
Author-email: n.kalis98@gmail.com
Requires-Python: >=3.7.1,<4.0
Classifier: Development Status :: 4 - Beta
Classifier: Intended Audience :: Developers
Classifier: License :: OSI Approved :: MIT License
Classifier: Operating System :: OS Independent
Classifier: Programming Language :: Python
Classifier: Programming Language :: Python :: 3
Classifier: Programming Language :: Python :: 3.8
Classifier: Programming Language :: Python :: 3.9
Classifier: Programming Language :: Python :: 3.10
Classifier: Programming Language :: Python :: 3.11
Classifier: Programming Language :: Python :: 3
Classifier: Programming Language :: Python :: 3.7
Classifier: Programming Language :: Python :: 3.8
Classifier: Programming Language :: Python :: 3.9
Classifier: Topic :: Software Development :: Libraries :: Python Modules
Classifier: Typing :: Typed
Project-URL: Documentation, https://nkalis.github.io/sunsolve
Project-URL: Repository, https://github.com/nkalis/sunsolve
